{
  "peliculas": [
    {
      "titulo": "Avengers: Endgame",
      "descripcion": "Los héroes de Marvel se unen para derrotar a Thanos y restaurar el equilibrio en el universo.",
      "idiomasDisponible": ["ESP", "ENG"],
      "restriccionEdad": "PG-13",
      "categorias": ["ACCION", "CIENCIA_FICCION"],
      "reparto": [
        {"nombre": "Robert Downey Jr.", "personaje": "Tony Stark / Iron Man"},
        {"nombre": "Chris Evans", "personaje": "Steve Rogers / Capitán América"},
        {"nombre": "Scarlett Johansson", "personaje": "Natasha Romanoff / Viuda Negra"}
      ]
    },
    {
      "titulo": "The Shawshank Redemption",
      "descripcion": "Dos hombres encuentran esperanza en una cárcel mientras forman una inesperada amistad.",
      "idiomasDisponible": ["ESP", "ENG"],
      "restriccionEdad": "R",
      "categorias": ["DRAMA"],
      "reparto": [
        {"nombre": "Tim Robbins", "personaje": "Andy Dufresne"},
        {"nombre": "Morgan Freeman", "personaje": "Ellis Boyd 'Red' Redding"}
      ]
    },
    {
      "titulo": "Inception",
      "descripcion": "Dom Cobb realiza atracos corporativos usando tecnología que permite el robo de secretos.",
      "idiomasDisponible": ["ESP", "ENG"],
      "restriccionEdad": "PG-13",
      "categorias": ["CIENCIA_FICCION", "ACCION"],
      "reparto": [
        {"nombre": "Leonardo DiCaprio", "personaje": "Dom Cobb"},
        {"nombre": "Joseph Gordon-Levitt", "personaje": "Arthur"}
      ]
    },
    {
      "titulo": "The Dark Knight",
      "descripcion": "Batman enfrenta al Joker, un criminal maestro que busca sumir a Gotham en el caos.",
      "idiomasDisponible": ["ESP", "ENG"],
      "restriccionEdad": "PG-13",
      "categorias": ["ACCION", "DRAMA"],
      "reparto": [
        {"nombre": "Christian Bale", "personaje": "Bruce Wayne / Batman"},
        {"nombre": "Heath Ledger", "personaje": "Joker"}
      ]
    },
    {
      "titulo": "Forrest Gump",
      "descripcion": "Forrest Gump vive una vida notable, influyendo en eventos importantes de la historia.",
      "idiomasDisponible": ["ESP", "ENG"],
      "restriccionEdad": "PG-13",
      "categorias": ["DRAMA"],
      "reparto": [
        {"nombre": "Tom Hanks", "personaje": "Forrest Gump"},
        {"nombre": "Robin Wright", "personaje": "Jenny Curran"}
      ]
    },
    {
      "titulo": "Pulp Fiction",
      "descripcion": "Varias historias se entrelazan en Los Ángeles, explorando el crimen y la redención.",
      "idiomasDisponible": ["ESP", "ENG"],
      "restriccionEdad": "R",
      "categorias": ["DRAMA", "CRIMEN"],
      "reparto": [
        {"nombre": "John Travolta", "personaje": "Vincent Vega"},
        {"nombre": "Samuel L. Jackson", "personaje": "Jules Winnfield"}
      ]
    },
    {
      "titulo": "The Matrix",
      "descripcion": "Neo descubre la verdad sobre su realidad y lidera una rebelión contra las máquinas.",
      "idiomasDisponible": ["ESP", "ENG"],
      "restriccionEdad": "R",
      "categorias": ["CIENCIA_FICCION", "ACCION"],
      "reparto": [
        {"nombre": "Keanu Reeves", "personaje": "Neo"},
        {"nombre": "Carrie-Anne Moss", "personaje": "Trinity"}
      ]
    },
    {
      "titulo": "The Godfather",
      "descripcion": "La familia Corleone enfrenta desafíos y traiciones en el mundo del crimen organizado.",
      "idiomasDisponible": ["ESP", "ENG"],
      "restriccionEdad": "R",
      "categorias": ["DRAMA", "CRIMEN"],
      "reparto": [
        {"nombre": "Marlon Brando", "personaje": "Vito Corleone"},
        {"nombre": "Al Pacino", "personaje": "Michael Corleone"}
      ]
    },
    {
      "titulo": "Schindler's List",
      "descripcion": "Oskar Schindler salva a judíos durante el Holocausto, mostrando la capacidad humana para el bien.",
      "idiomasDisponible": ["ESP", "ENG"],
      "restriccionEdad": "R",
      "categorias": ["DRAMA", "HISTORIA"],
      "reparto": [
        {"nombre": "Liam Neeson", "personaje": "Oskar Schindler"},
        {"nombre": "Ben Kingsley", "personaje": "Itzhak Stern"}
      ]
    },
    {
      "titulo": "The Silence of the Lambs",
      "descripcion": "Una agente del FBI busca la ayuda de Hannibal Lecter para atrapar a un asesino en serie.",
      "idiomasDisponible": ["ESP", "ENG"],
      "restriccionEdad": "R",
      "categorias": ["CRIMEN", "THRILLER"],
      "reparto": [
        {"nombre": "Jodie Foster", "personaje": "Clarice Starling"},
        {"nombre": "Anthony Hopkins", "personaje": "Hannibal Lecter"}
      ]
    },
  ]
}
